airfunctions/__init__.py
airfunctions/bundle.py
airfunctions/conditions.py
airfunctions/config.py
airfunctions/context.py
airfunctions/example.py
airfunctions/jsonata.py
airfunctions/jsonpath.py
airfunctions/poetry_utils.py
airfunctions/steps.py
airfunctions/terrapy.py
airfunctions-0.2.0.dist-info/METADATA
airfunctions-0.2.0.dist-info/WHEEL
airfunctions-0.2.0.dist-info/RECORD
