Metadata-Version: 2.3
Name: airfunctions
Version: 0.2.0
Summary: 
License: MIT
Author: Michał Murawski
Author-email: mmurawski777@gmail.com
Requires-Python: <4.0,>=3.10
Classifier: License :: OSI Approved :: MIT License
Classifier: Programming Language :: Python :: 3
Classifier: Programming Language :: Python :: 3.10
Classifier: Programming Language :: Python :: 3.11
Classifier: Programming Language :: Python :: 3.12
Classifier: Programming Language :: Python :: 3.13
Requires-Dist: poetry-plugin-lambda-build (>=1.0.8,<2.0.0)
